hashivault_vars/hashivault_vars.py
hashivault_vars-0.2.0.dist-info/LICENSE
hashivault_vars-0.2.0.dist-info/METADATA
hashivault_vars-0.2.0.dist-info/WHEEL
hashivault_vars-0.2.0.dist-info/top_level.txt
hashivault_vars-0.2.0.dist-info/RECORD
